LICENSE
MANIFEST.in
requirements.txt
setup.cfg
setup.py
test_requirements.txt
eth_token_index/__init__.py
eth_token_index/index.py
eth_token_index.egg-info/PKG-INFO
eth_token_index.egg-info/SOURCES.txt
eth_token_index.egg-info/dependency_links.txt
eth_token_index.egg-info/entry_points.txt
eth_token_index.egg-info/requires.txt
eth_token_index.egg-info/top_level.txt
eth_token_index/data/TokenUniqueSymbolIndex.bin
eth_token_index/data/TokenUniqueSymbolIndex.json
eth_token_index/data/TokenUniqueSymbolIndex.metadata.bin
eth_token_index/data/TokenUniqueSymbolIndex.metadata.json
eth_token_index/runnable/add.py
eth_token_index/runnable/list.py
eth_token_index/runnable/publish.py
eth_token_index/runnable/writer.py
tests/test_tokenindex.py